siren_client/__init__.py
siren_client/client.py
siren_client/compat.py
siren_client/entity.py
siren_client-1.0.0.dev1.dist-info/DESCRIPTION.rst
siren_client-1.0.0.dev1.dist-info/METADATA
siren_client-1.0.0.dev1.dist-info/metadata.json
siren_client-1.0.0.dev1.dist-info/RECORD
siren_client-1.0.0.dev1.dist-info/top_level.txt
siren_client-1.0.0.dev1.dist-info/WHEEL
siren_client-1.0.0.dev1.dist-info/zip-safe
