Metadata-Version: 2.0
Name: siren-client
Version: 1.0.0.dev1
Summary: Client for a Siren based Hypermedia API
Home-page: https://github.com/lonelyplanet/siren-client-python
Author: Will Wheatley
Author-email: will.wheatley@lonelyplanet.com.au
License: Apache 2.0
Keywords: siren hypermedia json
Platform: UNKNOWN
Classifier: Programming Language :: Python
Classifier: Intended Audience :: Developers
Classifier: Topic :: Internet :: WWW/HTTP
Classifier: Topic :: Internet :: WWW/HTTP :: Dynamic Content
Classifier: Topic :: Software Development :: Libraries
Classifier: License :: OSI Approved :: Apache Software License
Provides-Extra: testing
Requires-Dist: pytest; extra == 'testing'
Requires-Dist: mock; extra == 'testing'
Requires-Dist: requests; extra == 'testing'
Requires-Dist: simplejson; extra == 'testing'
